{
    "HeaderInfo": {
        "PlaylistName": "Tapmad Matches Metadata",
        "LastUpdate": "11:10 AM 06-07-2026",
        "Telegram": "https://t.me/livesportsplay",
        "Owner": "Md Sohanur Rahman Hady",
        "SpecialThanks": "Shuvo vai for contributing his premium Tapmad account."
    },
    "Stats": {
        "LiveCount": 0,
        "UpcomingCount": 4
    },
    "Matches": [
        {
            "EntityId": 14774,
            "VideoName": "Zimbabwe vs Bangladesh",
            "CategoryName": "Bangladesh Tour of Zimbabwe 2026",
            "StageName": "1st ODI",
            "EventStartDate": "2026-07-06 13:30:00",
            "Description": "The 1st ODI of the Bangladesh Tour of Zimbabwe 2026 marks the start of a three match Odi series. Watch Zimbabwe vs Bangladesh 1st Odi live in HD on tapmad, with official match coverage and uninterrupted streaming. These top-ranked white-ball teams, to begin with a strong squad, Zimbabwe cricket team focusing on balance and pace control. Bangladesh, led by Mehidy Hasan, rely on experienced player such as Litton Das to apply early pressure and dominate key phases.",
            "ThumbnailStandard": "https://d34080pnh6e62j.cloudfront.net/images/channels/ChannelFeaturedAppthumb/1783081316540x302.jpg",
            "ThumbnailTV": "https://d34080pnh6e62j.cloudfront.net/images/channels/ChannelTVImage/1783081316540x302.jpg",
            "IsFreeToWatch": false,
            "Status": "Upcoming",
            "CategoryId": 551,
            "UrlSlug": "zimbabwe-vs-bangladesh-1st-odi-live"
        },
        {
            "EntityId": 13963,
            "VideoName": "West Indies vs Sri Lanka",
            "CategoryName": "Sri Lanka Tour of West Indies 2026",
            "StageName": "2nd Test",
            "EventStartDate": "2026-07-06 20:00:00",
            "Description": "The 2nd Test of the  Sri Lanka Tour of West Indies 2026 marks the start of a two match test series. Watch West Indies vs Sri Lanka 2nd test live in HD on tapmad, with official match coverage and uninterrupted streaming. These top-ranked red-ball teams, to begin with a strong squad, West Indies will look to make the most of home conditions with a well-balanced squad, while Sri Lanka aim to challenge with a disciplined unit capable of competing in all aspects of the game. Both teams will be eager to gain an early advantage in the series.",
            "ThumbnailStandard": "https://d34080pnh6e62j.cloudfront.net/images/channels/ChannelFeaturedAppthumb/1782979314540x302.jpg",
            "ThumbnailTV": "https://d34080pnh6e62j.cloudfront.net/images/channels/ChannelTVImage/1782979314540x302.jpg",
            "IsFreeToWatch": false,
            "Status": "Upcoming",
            "CategoryId": 460,
            "UrlSlug": "west-indies-vs-sri-lanka-2nd-test-live"
        },
        {
            "EntityId": 14798,
            "VideoName": "England vs India",
            "CategoryName": "India Tour of England 2026",
            "StageName": "3rd T20I",
            "EventStartDate": "2026-07-07 22:30:00",
            "Description": "The 3rd T20 of the India Tour of England 2026 marks the start of a 5 match T20 series. Watch England vs India 3rd T20 live in HD on tapmad, with official match coverage and uninterrupted streaming. These top-ranked white-ball teams, to begin with a strong squad, England will look to make the most of home conditions with a well-balanced squad, while India aim to challenge with a disciplined unit capable of competing in all aspects of the game. Both teams will be eager to gain an early advantage in the series.",
            "ThumbnailStandard": "https://d34080pnh6e62j.cloudfront.net/images/channels/ChannelFeaturedAppthumb/1783232285540x302.jpg",
            "ThumbnailTV": "https://d34080pnh6e62j.cloudfront.net/images/channels/ChannelTVImage/1783232285540x302.jpg",
            "IsFreeToWatch": false,
            "Status": "Upcoming",
            "CategoryId": 573,
            "UrlSlug": "england-vs-india-3rd-t20-live"
        },
        {
            "EntityId": 14799,
            "VideoName": "England vs India",
            "CategoryName": "India Tour of England 2026",
            "StageName": "4th T20I",
            "EventStartDate": "2026-07-09 22:30:00",
            "Description": "The 4th T20 of the India Tour of England 2026 marks the start of a 5 match T20 series. Watch England vs India 4th T20 live in HD on tapmad, with official match coverage and uninterrupted streaming. These top-ranked white-ball teams, to begin with a strong squad, England will look to make the most of home conditions with a well-balanced squad, while India aim to challenge with a disciplined unit capable of competing in all aspects of the game. Both teams will be eager to gain an early advantage in the series.",
            "ThumbnailStandard": "https://d34080pnh6e62j.cloudfront.net/images/channels/ChannelFeaturedAppthumb/1783232533540x302.jpg",
            "ThumbnailTV": "https://d34080pnh6e62j.cloudfront.net/images/channels/ChannelTVImage/1783232533540x302.jpg",
            "IsFreeToWatch": false,
            "Status": "Upcoming",
            "CategoryId": 573,
            "UrlSlug": "england-vs-india-4th-t20-live"
        }
    ]
}